admin_table/.gitignore
admin_table/__init__.py
admin_table/application.py
admin_table/auth.py
admin_table/config.py
admin_table/modules/__init__.py
admin_table/modules/bases/__init__.py
admin_table/modules/bases/resolver.py
admin_table/modules/sqlalchemy_module.py
admin_table/py.typed
admin_table/ui/assets/index-CQLGe9gY.js
admin_table/ui/assets/index-CjWvYbXV.css
admin_table/ui/index.html
admin_table/views/__init__.py
admin_table/views/list_view.py
admin_table/wrappers/__init__.py
admin_table/wrappers/_base.py
admin_table/wrappers/fastapi_wrapper.py
admin_table/wrappers/flask_wrapper.py
admin_table-0.0.32.dist-info/LICENSE
admin_table-0.0.32.dist-info/METADATA
admin_table-0.0.32.dist-info/WHEEL
admin_table-0.0.32.dist-info/RECORD
