Metadata-Version: 2.3
Name: admin-table
Version: 0.0.32
Summary: Another Dashboard Library for displaying mostly tables
License: MIT
Author: Adam Verner
Author-email: averner@averner.cz
Requires-Python: >=3.11,<4.0
Classifier: License :: OSI Approved :: MIT License
Classifier: Programming Language :: Python :: 3
Classifier: Programming Language :: Python :: 3.11
Classifier: Programming Language :: Python :: 3.12
Classifier: Programming Language :: Python :: 3.13
Provides-Extra: fastapi
Requires-Dist: fastapi ; extra == "fastapi"
Requires-Dist: pyjwt (>=2.10.1,<3.0.0)
